[
   {
      "name": "Landing page",
      "title": "Ідеальний варіант для бізнесу, якому потрібна коротка, але змістовна, презентація",
      "subtitle": "Завдяки зручності такого формату, можна легко подати користувачу всю важливу інформацію та швидко підвести його до покупки",
      "why": "Обирайте цей тип сайту, якщо:",
      "reason": [
         {
            "text": "Ви хочете презентувати власний інфо-продукт, послугу, книгу і т.д."
         },
         {
            "text": "У вас невелика кількість продуктів (до 8)"
         },
         {
            "text": "Вам потрібне коротке портфоліо спеціаліста або сайт-візитка"
         }
      ]
   },
   {
      "name": "Багатосторінковий сайт",
      "title": "Величезне поле для креативу",
      "subtitle": "Ви можете використати будь-яку кількість сторінок для того, щоб розповісти про свій бізнес, показати свій продукт, презентувати компанію або просто поділитись корисною інформацією",
      "why": "Обирайте цей тип сайту, якщо:",
      "reason": [
         {
            "text": "Вам потрібно більше однієї сторінки на сайті"
         },
         {
            "text": "Ви плануєте зробити блог та/або особистий кабінет"
         },
         {
            "text": "На сайті передбачається будь-який інший додатковий функціонал"
         }
      ]
   },
   {
      "name": "Інтернет магазин",
      "title": "Зручний сайт для бізнесу, який дозволить користувачам:",
      "advantages": [
         {
            "text": "Швидко знайти потрібний товар"
         },
         {
            "text": "Зробити замовлення у будь-який час"
         }
      ],
      "subtitle": "Каталог, зручна фільтрація, особистий кабінет і продуманий до деталей інтерфейс точно збільшать кількість ваших клієнтів завдяки комфортному користуванню та легкому оформленню покупки",
      "why": "Обирайте цей тип сайту, якщо:",
      "reason": [
         {
            "text": "У вас більше 8 товарів"
         },
         {
            "text": "Вам потрібен каталог, корзина, особистий кабінет або інші сторінки такого типу"
         }
      ]
   },
   {
      "name": "Аудит сайту",
      "title": "Детальний аудит вашого сайту по всім можливим параметрам",
      "subtitle": "В аудиті розглядаються: дизайн, текст, конверсія, технічні данні, індексація пошуковими системами та багато інших характеристик",
      "why": "Аудит допоможе вам:",
      "reason": [
         {
            "text": "Побачити зроблені помилки"
         },
         {
            "text": "Знайти правильний підхід до своїх клієнтів"
         },
         {
            "text": "В рази збільшити показник конверсії"
         },
         {
            "text": "Отримати десятки нових ідей для сайту"
         },
         {
            "text": "та багато чого іншого."
         }
      ]
   },
   {
      "name": "Індивідуальна консультація",
      "title": "Ідеальний початок для просування вашого бізнесу в інтернеті",
      "subtitle": "Окрім готового фундаменту для власного сайту, ви отримаєте рекомендації, які допоможуть вам швидко досягнути успіху в просуванні свого бізнесу",
      "reason": [
         {
            "text": "Консультація триває 1.5 години в онлайн форматі"
         },
         {
            "text": "Ви можете вказати додаткові запитання щодо вашого бізнесу та, за попереднім узгодженням, я включу їх в нашу консультацію"
         }
      ]
   },
   {
      "name": "Демонстрація",
      "title": "Це показ вашого сайту на останній стадії розробки",
      "subtitle": "На ньому ви побачите вже готовий продукт, як він працює, та всі його переваги",
      "why": "На демонстрації ви зможете:",
      "reason": [
         {
            "text": "Побачити готовий продукт"
         },
         {
            "text": "Внести останні виправлення (якщо це не глобальні зміни)"
         },
         {
            "text": "Доторкнутись своїми руками, до сайту, як користувач(якщо є панель адміністрації, то і як адміністратор)"
         },
         {
            "text": "Якщо є панель адміністрації, то навчитись користуватись нею(додатково отримаєте відео інструкцію з усіма можливостями)"
         }
      ]
   }
]